{
  "parent": "minecraft:recipes/root",
  "criteria": {
    "has_pez": {
      "conditions": {
        "items": [
          {
            "items": "candycraftce:pez"
          }
        ]
      },
      "trigger": "minecraft:inventory_changed"
    },
    "has_the_recipe": {
      "conditions": {
        "recipe": "candycraftce:pez_chestplate"
      },
      "trigger": "minecraft:recipe_unlocked"
    }
  },
  "requirements": [
    [
      "has_the_recipe",
      "has_pez"
    ]
  ],
  "rewards": {
    "recipes": [
      "candycraftce:pez_chestplate"
    ]
  }
}